financial_reports/__init__.py
financial_reports/client.py
financial_reports/logger.py
financial_reports/models.py
financial_reports-0.1.0.dist-info/METADATA
financial_reports-0.1.0.dist-info/WHEEL
financial_reports-0.1.0.dist-info/licenses/LICENSE
financial_reports-0.1.0.dist-info/RECORD
