Metadata-Version: 2.4
Name: financial-reports
Version: 0.1.0
Summary: Official Python SDK for Financial Reports API
Project-URL: Homepage, https://github.com/financial-reports/financial-reports-python
Project-URL: Documentation, https://docs.financialreports.eu
Author-email: Financial Reports Team <team@financialreports.eu>
License-File: LICENSE
Classifier: License :: OSI Approved :: MIT License
Classifier: Operating System :: OS Independent
Classifier: Programming Language :: Python :: 3
Requires-Python: >=3.9
Requires-Dist: aiohttp>=3.8.0
Requires-Dist: pydantic>=2.0.0
Provides-Extra: test
Requires-Dist: pytest-asyncio>=0.23.0; extra == 'test'
Requires-Dist: pytest-cov>=4.1.0; extra == 'test'
Requires-Dist: pytest>=7.0.0; extra == 'test'
